{
    "videoNames":
    [
        {"name":"lethalcompany.mp4"},
        {"name":"outro.mov"},
        {"name":"rayas.mp4"},
        {"name":"mcparkour.mp4"},
        {"name":"najlepszefilmy.mp4"},
        {"name":"chinese boing sound effect.mp3"},
        {"name":"banerv2.png"},
        {"name":"banerv5.png"},
        {"name":"baner.png"},
        {"name":"banerv7.png"},
        {"name":"garrysmod1.mp4"},
        {"name":"koniecszefa.mp4"},
        {"name":"wzlotiupadek.mp4"},
        {"name":"mp4.mp4"},
        {"name":"bykismp1.mp4"},
        {"name":"gradlarayasa.mp4"},
        {"name":"rec1.mov"},
        {"name":"spoko (1).mp3"},
        {"name":"zgloszenie_klocuchowy.mp4"},
        {"name":"marioparty_themovie.mp4"},
        {"name":"bitcoin_miner.mp4"},
        {"name":"apology_video.mp4"},
        {"name":"mordcast.mp4"},
        {"name":"prezentacje.mp4"},
        {"name":"marta.png"},
        {"name":"kd dochodzenie.mp4"},
        {"name":"wyzwanie gigachada.mp4"},
        {"name":"wyznanie sasiada.wav"},
        {"name":"porytyshort.mp4"},
        {"name":"nowyfilmshort.mp4"},
        {"name":"skibidi.mp4"},
        {"name":"reklama k###### (2024 ver.).mp4"},
        {"name":"burgerki.mp4"},
        {"name":"wyznanie sasiada.wav"},
        {"name":"Dla Chlopa (FULL EP).mp3"},
        {"name":"valorant short.mp4"},
        {"name":"zapomniani youtuberzy 8.mp4"},
        {"name":"dlaczego r6s TO KUPA.mp3"},
        {"name":"O_O.mp4"},
        {"name":"juicowanie killera przez 57 sekund.mp4"},
        {"name":"gameplay z SLASH CO #1.mp4"},
        {"name":"witaj sasiedzie.mp4"},
        {"name":"sasiad z gory (2).mp4"},
        {"name":"film.mp4"},
        {"name":"blednekoloR.mp4"},
        {"name":"burgeryzosiedla_promo.mp4"},
        {"name":"mordnews 2024 edition.mp4"},
        {"name":"co dalej?.mp4"},
        {"name":"film informacyjny.mp4"},
        {"name":"        .mp4"},
        {"name":"zakazany film.mp4"}
    ]
}